README.rst
setup.py
src/collective/__init__.py
src/collective.cmisquery.egg-info/PKG-INFO
src/collective.cmisquery.egg-info/SOURCES.txt
src/collective.cmisquery.egg-info/dependency_links.txt
src/collective.cmisquery.egg-info/namespace_packages.txt
src/collective.cmisquery.egg-info/not-zip-safe
src/collective.cmisquery.egg-info/requires.txt
src/collective.cmisquery.egg-info/top_level.txt
src/collective/cmisquery/__init__.py
src/collective/cmisquery/interfaces.py
src/collective/cmisquery/browser/__init__.py
src/collective/cmisquery/browser/forms.py
src/collective/cmisquery/browser/views.py
src/collective/cmisquery/content/__init__.py
src/collective/cmisquery/content/cmisquery.py