Metadata-Version: 1.1
Name: collective.cmisquery
Version: 1.0
Summary: CMIS repository query for Plone
Home-page: http://pypi.python.org/pypi/collective.cmisquery
Author: Sylvain Viollon
Author-email: sylvain@infrae.com
License: GPL
Keywords: CMIS connection query browser plone
Platform: UNKNOWN
Classifier: Framework :: Plone
Classifier: Framework :: Zope2
